cv2_plt_imshow/__init__.py
cv2_plt_imshow/imshow.py
tests/__init__.py
cv2_plt_imshow-0.0.1.dist-info/LICENSE
cv2_plt_imshow-0.0.1.dist-info/METADATA
cv2_plt_imshow-0.0.1.dist-info/WHEEL
cv2_plt_imshow-0.0.1.dist-info/top_level.txt
cv2_plt_imshow-0.0.1.dist-info/RECORD
