Metadata-Version: 2.1
Name: cv2-plt-imshow
Version: 0.0.1
Summary: Using matplotlib_imshow for images read by cv2
Home-page: https://github.com/rs9899/cv2_plt_imshow
Author: Rupesh
Author-email: rupesh95903@gmail.com
License: MIT
Project-URL: Bug Reports, https://github.com/rs9899/cv2_plt_imshow/issues
Project-URL: Source, https://github.com/rs9899/cv2_plt_imshow
Keywords: cv2 imshow pyplot cv2_imshow matplotlib
Platform: UNKNOWN
Classifier: Programming Language :: Python :: 3
Classifier: License :: OSI Approved :: MIT License
Classifier: Operating System :: OS Independent
Requires-Python: >=3.6
